bookirds/__init__.py
bookirds/bsplines.py
bookirds/covar.py
bookirds/cross_gamma.py
bookirds/curves.py
bookirds/dual.py
bookirds/mid_market.py
bookirds/pca.py
bookirds/swaptions.py
bookirds3-1.1.1.dist-info/LICENSE
bookirds3-1.1.1.dist-info/METADATA
bookirds3-1.1.1.dist-info/WHEEL
bookirds3-1.1.1.dist-info/top_level.txt
bookirds3-1.1.1.dist-info/RECORD
