Metadata-Version: 2.1
Name: bookirds3
Version: 1.1.1
Summary: Pricing and Trading Interest Rate Derivatives
Author: J H M Darbyshire
License: GNU GENERAL PUBLIC LICENSE
Project-URL: Homepage, https://github.com/attack68/book_irds3
Keywords: interest rate,derivatives,swaps
Requires-Python: >=3.7
License-File: LICENSE
Requires-Dist: numpy (>=1.21.5)
Requires-Dist: scipy (>=1.8.0)
Provides-Extra: dev
Requires-Dist: pytest (>=7.0.1) ; extra == 'dev'
Requires-Dist: jupyterlab (>=3.3.1) ; extra == 'dev'
Requires-Dist: matplotlib (>=3.5.1) ; extra == 'dev'
Requires-Dist: numba (>=0.55.1) ; extra == 'dev'
Requires-Dist: pandas (>=1.4.1) ; extra == 'dev'
